unesco_reader/__init__.py
unesco_reader/api.py
unesco_reader/config.py
unesco_reader/core.py
unesco_reader/exceptions.py
unesco_reader-3.0.0.dist-info/LICENSE
unesco_reader-3.0.0.dist-info/METADATA
unesco_reader-3.0.0.dist-info/WHEEL
unesco_reader-3.0.0.dist-info/RECORD
