Metadata-Version: 2.1
Name: unesco-reader
Version: 3.0.0
Summary: Pythonic access to UNESCO data
License: MIT
Author: Luca Picci
Requires-Python: >=3.10,<4
Classifier: License :: OSI Approved :: MIT License
Classifier: Programming Language :: Python :: 3
Classifier: Programming Language :: Python :: 3.10
Classifier: Programming Language :: Python :: 3.11
Classifier: Programming Language :: Python :: 3.12
Classifier: Programming Language :: Python :: 3.13
Requires-Dist: pandas (>=2.2.1,<3.0.0)
Requires-Dist: requests (>=2.32.3,<3.0.0)
